trentubuddy/__init__.py
trentubuddy/bot.py
trentubuddy/cogs/commands/booking.py
trentubuddy/cogs/commands/contact.py
trentubuddy/cogs/commands/help.py
trentubuddy/cogs/commands/web_scraper_commands.py
trentubuddy/cogs/events/listeners.py
trentubuddy/env/__init__.py
trentubuddy/scripts/__init__.py
trentubuddy/scripts/ac_link_scraiper.py
trentubuddy/scripts/cs_specialty_scraper.py
trentubuddy/scripts/helpers.py
trentubuddy-1.1.0.dist-info/LICENSE
trentubuddy-1.1.0.dist-info/METADATA
trentubuddy-1.1.0.dist-info/WHEEL
trentubuddy-1.1.0.dist-info/entry_points.txt
trentubuddy-1.1.0.dist-info/top_level.txt
trentubuddy-1.1.0.dist-info/RECORD
